langgraph_codegen/__init__.py
langgraph_codegen/gen_graph.py
langgraph_codegen/graph.py
langgraph_codegen/lgcodegen.py
langgraph_codegen/repl.py
langgraph_codegen/data/examples/bea_agent.txt
langgraph_codegen/data/examples/bea_evaluator_optimizer.txt
langgraph_codegen/data/examples/bea_orchestrator_worker.txt
langgraph_codegen/data/examples/bea_parallelization.txt
langgraph_codegen/data/examples/bea_prompt_chaining.txt
langgraph_codegen/data/examples/define_state.txt
langgraph_codegen/data/examples/fanin.graph
langgraph_codegen/data/examples/guard.graph
langgraph_codegen/data/examples/multi_agent_collaboration.graph
langgraph_codegen/data/examples/plan_and_execute.graph
langgraph_codegen/data/examples/rag.graph
langgraph_codegen/data/examples/react_agent.graph
langgraph_codegen/data/examples/simple.graph
langgraph_codegen/data/examples/supervisor.graph
langgraph_codegen-1.0.2.dist-info/licenses/LICENSE
langgraph_codegen-1.0.2.dist-info/METADATA
langgraph_codegen-1.0.2.dist-info/WHEEL
langgraph_codegen-1.0.2.dist-info/entry_points.txt
langgraph_codegen-1.0.2.dist-info/top_level.txt
langgraph_codegen-1.0.2.dist-info/RECORD
