Metadata-Version: 2.4
Name: langgraph-codegen
Version: 1.0.2
Summary: Generate graph code from DSL for LangGraph framework
Home-page: https://github.com/jojohannsen/langgraph-codegen
Author: Johannes Johannsen
Author-email: johannes.johannsen@gmail.com
Classifier: Programming Language :: Python :: 3
Classifier: License :: OSI Approved :: MIT License
Classifier: Operating System :: OS Independent
Requires-Python: >=3.6
License-File: LICENSE
Requires-Dist: colorama>=0.4.6
Requires-Dist: rich>=13.3.1
Dynamic: author
Dynamic: author-email
Dynamic: classifier
Dynamic: description
Dynamic: description-content-type
Dynamic: home-page
Dynamic: license-file
Dynamic: requires-dist
Dynamic: requires-python
Dynamic: summary
